rules/__init__.py
rules/apps.py
rules/permissions.py
rules/predicates.py
rules/rulesets.py
rules/contrib/__init__.py
rules/contrib/admin.py
rules/contrib/models.py
rules/contrib/rest_framework.py
rules/contrib/views.py
rules/templatetags/__init__.py
rules/templatetags/rules.py
rules-3.3.dist-info/LICENSE
rules-3.3.dist-info/METADATA
rules-3.3.dist-info/WHEEL
rules-3.3.dist-info/top_level.txt
rules-3.3.dist-info/RECORD
