Metadata-Version: 2.1
Name: rules
Version: 3.3
Summary: Awesome Django authorization, without the database
Home-page: http://github.com/dfunckt/django-rules
Author: Akis Kesoglou
Author-email: akiskesoglou@gmail.com
Maintainer: Akis Kesoglou
Maintainer-email: akiskesoglou@gmail.com
License: MIT
Platform: UNKNOWN
Classifier: Development Status :: 5 - Production/Stable
Classifier: Environment :: Web Environment
Classifier: Framework :: Django
Classifier: Intended Audience :: Developers
Classifier: License :: OSI Approved :: MIT License
Classifier: Operating System :: OS Independent
Classifier: Programming Language :: Python
Classifier: Programming Language :: Python :: 3
Classifier: Programming Language :: Python :: 3.7
Classifier: Programming Language :: Python :: 3.8
Classifier: Programming Language :: Python :: 3.9
Classifier: Programming Language :: Python :: 3.10
License-File: LICENSE
